py_tata/__init__.py
py_tata/cli/__init__.py
py_tata/cli/app.py
py_tata/core/__init__.py
py_tata/core/builder/__init__.py
py_tata/core/builder/task_builder.py
py_tata/core/command_executor/__init__.py
py_tata/core/command_executor/asyncio_command_executor.py
py_tata/core/loader/__init__.py
py_tata/core/loader/exceptions.py
py_tata/core/loader/yaml_loader.py
py_tata/core/runner/__init__.py
py_tata/core/runner/runner.py
py_tata/tasks/__init__.py
py_tata/tasks/check_hostname/__init__.py
py_tata/tasks/check_hostname/builder.py
py_tata/tasks/check_hostname/task.py
py_tata/tasks/check_hostname/validation_model.py
py_tata/tasks/check_ping/__init__.py
py_tata/tasks/check_ping/builder.py
py_tata/tasks/check_ping/task.py
py_tata/tasks/check_ping/validation_model.py
py_tata/tasks/linux_check_ip_forwarding/__init__.py
py_tata/tasks/linux_check_ip_forwarding/builder.py
py_tata/tasks/linux_check_ip_forwarding/ipv4/__init__.py
py_tata/tasks/linux_check_ip_forwarding/ipv4/builder.py
py_tata/tasks/linux_check_ip_forwarding/ipv4/task.py
py_tata/tasks/linux_check_ip_forwarding/ipv4/validation_model.py
py_tata/tasks/linux_check_ip_forwarding/ipv6/__init__.py
py_tata/tasks/linux_check_ip_forwarding/ipv6/builder.py
py_tata/tasks/linux_check_ip_forwarding/ipv6/task.py
py_tata/tasks/linux_check_ip_forwarding/ipv6/validation_model.py
py_tata/tasks/linux_check_ip_forwarding/task_abc.py
py_tata/tasks/task_result.py
py_tata/tasks/validation_model.py
py_tata-0.1.6.dist-info/entry_points.txt
py_tata-0.1.6.dist-info/LICENSE
py_tata-0.1.6.dist-info/METADATA
py_tata-0.1.6.dist-info/WHEEL
py_tata-0.1.6.dist-info/RECORD
