Metadata-Version: 2.1
Name: py_tata
Version: 0.1.6
Summary: 
Author: Sviatoslav Bobryshev
Author-email: wstswsb@gmail.com
Requires-Python: >=3.10.11,<4.0.0
Classifier: Programming Language :: Python :: 3
Classifier: Programming Language :: Python :: 3.11
Classifier: Programming Language :: Python :: 3.12
Requires-Dist: icmplib (>=3.0.4,<4.0.0)
Requires-Dist: pydantic (>=2.4.2,<3.0.0)
Requires-Dist: pyyaml (>=6.0.1,<7.0.0)
Requires-Dist: rich (>=13.6.0,<14.0.0)
Requires-Dist: typer (>=0.9.0,<0.10.0)
